microjson/__init__.py
microjson/automodel.py
microjson/examples/__init__.py
microjson/examples/df_to_microjson.py
microjson/examples/index.html
microjson/examples/load_validate.py
microjson/examples/readtiles.py
microjson/examples/tiles/tiled_example/0/0/0.json
microjson/examples/tiles/tiled_example/1/0/0.json
microjson/examples/tiles/tiled_example/1/0/1.json
microjson/examples/tiles/tiled_example/1/1/0.json
microjson/examples/tiles/tiled_example/1/1/1.json
microjson/examples/tiles/tiled_example/2/0/0.json
microjson/examples/tiles/tiled_example/2/0/1.json
microjson/examples/tiles/tiled_example/2/0/2.json
microjson/examples/tiles/tiled_example/2/0/3.json
microjson/examples/tiles/tiled_example/2/1/0.json
microjson/examples/tiles/tiled_example/2/1/1.json
microjson/examples/tiles/tiled_example/2/1/2.json
microjson/examples/tiles/tiled_example/2/1/3.json
microjson/examples/tiles/tiled_example/2/2/0.json
microjson/examples/tiles/tiled_example/2/2/1.json
microjson/examples/tiles/tiled_example/2/2/2.json
microjson/examples/tiles/tiled_example/2/2/3.json
microjson/examples/tiles/tiled_example/2/3/0.json
microjson/examples/tiles/tiled_example/2/3/1.json
microjson/examples/tiles/tiled_example/2/3/2.json
microjson/examples/tiles/tiled_example/2/3/3.json
microjson/examples/tiles/tiled_example.json
microjson/examples/tiling.py
microjson/examples/tiling_demo.ipynb
microjson/fileutils.py
microjson/geojson_model.py
microjson/microjson2vt/LICENSE
microjson/microjson2vt/__init__.py
microjson/microjson2vt/clip.py
microjson/microjson2vt/convert.py
microjson/microjson2vt/feature.py
microjson/microjson2vt/microjson2vt.py
microjson/microjson2vt/simplify.py
microjson/microjson2vt/tile.py
microjson/microjson2vt/transform.py
microjson/microjson2vt/utils.py
microjson/microjson2vt/vt2geojson.py
microjson/microjson2vt/wrap.py
microjson/model.py
microjson/polygen.py
microjson/provenance.py
microjson/roundtrip.py
microjson/tilehandler.py
microjson/tilemodel.py
microjson/tilereader.py
microjson-0.4.2.dist-info/LICENSE
microjson-0.4.2.dist-info/METADATA
microjson-0.4.2.dist-info/WHEEL
microjson-0.4.2.dist-info/RECORD
