Metadata-Version: 2.3
Name: microjson
Version: 0.4.2
Summary: MicroJSON is a library for validating, parsing, and manipulating MicroJSON data.
License: MIT
Keywords: json,microscopy,microjson
Author: Bengt Ljungquist
Author-email: bengt.ljungquist@nextonicsolutions.com
Requires-Python: >=3.9.15,<3.14
Classifier: License :: OSI Approved :: MIT License
Classifier: Programming Language :: Python
Classifier: Programming Language :: Python :: 3
Classifier: Programming Language :: Python :: 3.10
Classifier: Programming Language :: Python :: 3.11
Classifier: Programming Language :: Python :: 3.12
Classifier: Programming Language :: Python :: 3.13
Provides-Extra: all
Requires-Dist: bfio[all] (==2.4.6) ; extra == "all"
Requires-Dist: filepattern (>=2.0.1,<3.0.0) ; extra == "all"
Requires-Dist: geojson (>=3.1.0,<4.0.0)
Requires-Dist: geojson-pydantic (>=1.2.0,<2.0.0)
Requires-Dist: geojson2vt (>=1.0.1,<2.0.0)
Requires-Dist: geopandas (>=1.0.1,<2.0.0)
Requires-Dist: jsonschema (>=4.23.0,<5.0.0)
Requires-Dist: mapbox-vector-tile (>=2.1.0,<3.0.0)
Requires-Dist: matplotlib (>=3.5.1,<4.0.0) ; extra == "all"
Requires-Dist: protobuf (>=5.29.3,<6.0.0)
Requires-Dist: pyarrow (>=19.0.1,<20.0.0)
Requires-Dist: pydantic (>=2.3.0,<3.0.0)
Requires-Dist: scikit-image (>=0.20.0,<0.21.0) ; extra == "all"
Requires-Dist: scipy (>=1.8) ; extra == "all"
Requires-Dist: shapely (>=2.0.6,<3.0.0)
Requires-Dist: vaex-core (>=4.8.0,<5.0.0) ; extra == "all"
Project-URL: Documentation, https://polusai.github.io/microjson/
Project-URL: Source, https://github.com/polusai/microjson
Project-URL: Tracker, https://github.com/polusai/microjson/issues
